Synhtet/Synhtet.py
Synhtet/__init__.py
Synhtet-0.1.0.dist-info/LICENSE
Synhtet-0.1.0.dist-info/METADATA
Synhtet-0.1.0.dist-info/WHEEL
Synhtet-0.1.0.dist-info/top_level.txt
Synhtet-0.1.0.dist-info/RECORD
