Metadata-Version: 2.1
Name: Synhtet
Version: 0.1.0
Summary: A templates module for business analytics peers
Home-page: UNKNOWN
Author: Htet Aung Kyaw
Author-email: <hank.lo.kyaw@gmail.com>
License: UNKNOWN
Keywords: python,business analysis,templates,MBAN,syntax,example scripts
Platform: UNKNOWN
Classifier: Development Status :: 1 - Planning
Classifier: Intended Audience :: Developers
Classifier: Programming Language :: Python :: 3
Classifier: Operating System :: Unix
Classifier: Operating System :: MacOS :: MacOS X
Classifier: Operating System :: Microsoft :: Windows
License-File: LICENSE
Requires-Dist: seaborn
Requires-Dist: matplotlib
Requires-Dist: sklearn
Requires-Dist: numpy
